act_ratelimit/__init__.py
act_ratelimit/backends.py
act_ratelimit/constants.py
act_ratelimit/depends.py
act_ratelimit-1.0.0.dist-info/LICENSE
act_ratelimit-1.0.0.dist-info/WHEEL
act_ratelimit-1.0.0.dist-info/METADATA
act_ratelimit-1.0.0.dist-info/RECORD
