Metadata-Version: 2.3
Name: act-ratelimit
Version: 1.0.0
Summary: A simple rate limiter for FastAPI.
Author-email: Christopher <rayakame@proton.me>
Requires-Python: >=3.10.0
Classifier: License :: OSI Approved :: MIT License
Requires-Dist: fastapi~=0.115.8
Requires-Dist: nox==2024.10.9 ; extra == "dev"
Requires-Dist: towncrier==24.8.0 ; extra == "dev-changelog"
Requires-Dist: ruff==0.9.4 ; extra == "dev-format"
Requires-Dist: flit==3.10.1 ; extra == "dev-release"
Requires-Dist: pytest>=8.3.2, <9 ; extra == "dev-test"
Requires-Dist: pytest-asyncio>=0.23.8, <0.26 ; extra == "dev-test"
Requires-Dist: pytest-cov>=5.0.0, <7 ; extra == "dev-test"
Requires-Dist: pytest-randomly>=3.15.0, <4 ; extra == "dev-test"
Requires-Dist: pyright==1.1.393 ; extra == "dev-typecheck"
Requires-Dist: redis==5.2.1 ; extra == "redis"
Requires-Dist: valkey==6.0.2 ; extra == "valkey"
Project-URL: Home, https://github.com/Act-App/fastapi-ratelimit
Provides-Extra: dev
Provides-Extra: dev-changelog
Provides-Extra: dev-format
Provides-Extra: dev-release
Provides-Extra: dev-test
Provides-Extra: dev-typecheck
Provides-Extra: redis
Provides-Extra: valkey
